{
  "h_mags": "0",
  "h_anime": "0",
  "hcg": "0",
  "ddb_objects": "0",
  "ddb_samples": "0",
  "pixiv": "1",
  "pixivhistorical": "1",
  "anime": "0",
  "seiga_illust": "1",
  "danbooru": "1",
  "drawr": "0",
  "nijie": "1",
  "yande.re": "1",
  "animeop": "0",
  "IMDb": "0",
  "Shutterstock": "0",
  "FAKKU": "0",
  "H_MISC_(nhentai)": "1",
  "2d_market": "0",
  "medibang": "0",
  "Anime": "0",
  "H_Anime": "0",
  "Movies": "0",
  "Shows": "0",
  "gelbooru": "1",
  "konachan": "1",
  "sankaku": "1",
  "anime_pictures": "0",
  "e621": "0",
  "idol_complex": "0",
  "bcy_illust": "0",
  "bcy_cosplay": "0",
  "portalgraphics": "0",
  "dA": "0",
  "pawoo": "0",
  "madokami": "0",
  "mangadex": "0",
  "H_Misc_(ehentai)": "1",
  "ArtStation": "0",
  "FurAffinity": "0",
  "Twitter": "1",
  "Furry_Network": "0",
  "Kemono": "1",
  "Skeb": "1"
}